pytest_topo/__init__.py
pytest_topo/plugin.py
pytest_topo/topo.py
pytest_topo-1.1.0.dist-info/METADATA
pytest_topo-1.1.0.dist-info/WHEEL
pytest_topo-1.1.0.dist-info/entry_points.txt
pytest_topo-1.1.0.dist-info/licenses/LICENSE
pytest_topo-1.1.0.dist-info/RECORD
