Metadata-Version: 2.3
Name: pytest-topo
Version: 1.1.0
Summary: Topological sorting for pytest
Project-URL: Homepage, https://github.com/Nick-Sullivan/pytest-topo
Project-URL: Issues, https://github.com/Nick-Sullivan/pytest-topo/issues
Author-email: Nick Sullivan <nick.dave.sullivan@gmail.com>
License-File: LICENSE
Classifier: License :: OSI Approved :: MIT License
Classifier: Operating System :: OS Independent
Classifier: Programming Language :: Python :: 3
Requires-Python: >=3.7
Requires-Dist: networkx>=2.5
Requires-Dist: pytest>=7.0.0
Provides-Extra: test
Requires-Dist: ruff>=0.4.6; extra == 'test'
